{"cameraMode":{"drawMode":0,"name":"Shaded","section":"Shading Mode"},"sceneLighting":true,"audioPlay":false,"sceneViewState":{"showFog":true,"showMaterialUpdate":false,"showSkybox":true,"showFlares":true,"showImageEffects":true,"showParticleSystems":true},"in2DMode":false,"pivot":{"x":-221.66136169433595,"y":-14.167214393615723,"z":-246.7229766845703},"rotation":{"x":0.05402342230081558,"y":-0.5715833306312561,"z":0.037846047431230548,"w":0.8180491328239441},"size":216.5892791748047,"orthographic":false}