{"cameraMode":{"drawMode":0,"name":"Shaded","section":"Shading Mode"},"sceneLighting":true,"audioPlay":false,"sceneViewState":{"showFog":true,"showMaterialUpdate":false,"showSkybox":true,"showFlares":true,"showImageEffects":true,"showParticleSystems":true},"in2DMode":false,"pivot":{"x":15.826761245727539,"y":5.402035713195801,"z":-150.89797973632813},"rotation":{"x":0.38922256231307986,"y":0.3415549695491791,"z":-0.1580202877521515,"w":0.8408308029174805},"size":126.64544677734375,"orthographic":false}